{
  "https://feeds.feedburner.com/ndtvnews-world-news": "2025-03-01T09:25:40.000Z",
  "https://feeds.feedburner.com/ndtvnews-india-news": "2025-03-01T10:03:47.000Z",
  "https://feeds.feedburner.com/ndtvnews-trending-news": "2025-03-01T03:07:28.000Z",
  "https://feeds.feedburner.com/ndtvsports-cricket": "2025-03-01T07:01:22.000Z",
  "https://feeds.feedburner.com/gadgets360-latest": "2025-02-28T14:35:30.000Z",
  "https://feeds.feedburner.com/ndtvmovies-latest": "2025-03-01T09:02:57.000Z",
  "https://feeds.feedburner.com/ndtvsports-latest": "2025-03-01T08:03:34.000Z",
  "https://feeds.feedburner.com/ndtvprofit-latest": "2024-07-23T08:53:57.000Z",
  "https://feeds.feedburner.com/ndtvnews-top-stories": "2025-03-01T03:07:00.000Z",
  "https://feeds.feedburner.com/ndtvnews-latest": "2025-03-01T08:35:02.000Z"
}