{
  "https://feeds.feedburner.com/ndtvnews-world-news": "2025-06-15T01:26:39.000Z",
  "https://feeds.feedburner.com/ndtvnews-india-news": "2025-06-14T19:06:42.000Z",
  "https://feeds.feedburner.com/ndtvnews-trending-news": "2025-06-14T18:20:17.000Z",
  "https://feeds.feedburner.com/ndtvsports-cricket": "2025-06-14T18:20:17.000Z",
  "https://feeds.feedburner.com/gadgets360-latest": "2025-06-14T15:04:07.000Z",
  "https://feeds.feedburner.com/ndtvmovies-latest": "2025-06-14T15:13:42.000Z",
  "https://feeds.feedburner.com/ndtvsports-latest": "2025-06-14T18:24:17.000Z",
  "https://feeds.feedburner.com/ndtvprofit-latest": "2025-06-13T14:25:41.000Z",
  "https://feeds.feedburner.com/ndtvnews-top-stories": "2025-06-14T19:06:42.000Z",
  "https://feeds.feedburner.com/ndtvnews-latest": "2025-06-14T19:06:42.000Z"
}