{
  "https://feeds.feedburner.com/ndtvnews-world-news": "2025-04-29T21:25:02.000Z",
  "https://feeds.feedburner.com/ndtvnews-india-news": "2025-04-30T05:01:53.000Z",
  "https://feeds.feedburner.com/ndtvnews-trending-news": "2025-04-30T01:52:43.000Z",
  "https://feeds.feedburner.com/ndtvsports-cricket": "2025-04-30T03:47:02.000Z",
  "https://feeds.feedburner.com/gadgets360-latest": "2025-04-29T16:05:50.000Z",
  "https://feeds.feedburner.com/ndtvmovies-latest": "2025-04-30T04:41:43.000Z",
  "https://feeds.feedburner.com/ndtvsports-latest": "2025-04-30T04:39:43.000Z",
  "https://feeds.feedburner.com/ndtvprofit-latest": "2025-04-29T04:07:01.000Z",
  "https://feeds.feedburner.com/ndtvnews-top-stories": "2025-04-30T03:25:22.000Z",
  "https://feeds.feedburner.com/ndtvnews-latest": "2025-04-29T10:20:21.000Z"
}