{
  "https://feeds.feedburner.com/ndtvnews-world-news": "2025-07-02T17:11:40.000Z",
  "https://feeds.feedburner.com/ndtvnews-india-news": "2025-07-02T19:26:04.000Z",
  "https://feeds.feedburner.com/ndtvnews-trending-news": "2025-07-02T11:19:06.000Z",
  "https://feeds.feedburner.com/ndtvsports-cricket": "2025-07-01T16:21:28.000Z",
  "https://feeds.feedburner.com/gadgets360-latest": "2025-07-02T14:23:22.000Z",
  "https://feeds.feedburner.com/ndtvmovies-latest": "2025-07-02T12:58:12.000Z",
  "https://feeds.feedburner.com/ndtvsports-latest": "2025-07-02T17:53:59.000Z",
  "https://feeds.feedburner.com/ndtvprofit-latest": "2025-07-01T16:12:56.000Z",
  "https://feeds.feedburner.com/ndtvnews-top-stories": "2025-07-02T18:56:17.000Z",
  "https://feeds.feedburner.com/ndtvnews-latest": "2025-07-02T18:24:52.000Z"
}